open3d_ros2_helper/__init__.py
open3d_ros2_helper/open3d_ros2_helper.py
open3d_ros2_helper-0.1.0.0.dist-info/licenses/LICENSE
open3d_ros2_helper-0.1.0.0.dist-info/METADATA
open3d_ros2_helper-0.1.0.0.dist-info/WHEEL
open3d_ros2_helper-0.1.0.0.dist-info/top_level.txt
open3d_ros2_helper-0.1.0.0.dist-info/RECORD
