Metadata-Version: 2.4
Name: open3d_ros2_helper
Version: 0.1.0.0
Summary: A helper tool for jointly using open3d and ROS2
Home-page: https://github.com/olanrewajufarooq/open3d-ros2-helper
Author: Farooq Olanrewaju
Author-email: olanrewajufarooq@yahoo.com
License: MIT
Classifier: Programming Language :: Python :: 3
Classifier: Operating System :: OS Independent
Requires-Python: >=3.6
License-File: LICENSE
Requires-Dist: open3d>=0.17.0
Dynamic: author
Dynamic: author-email
Dynamic: classifier
Dynamic: description
Dynamic: description-content-type
Dynamic: home-page
Dynamic: license
Dynamic: license-file
Dynamic: requires-dist
Dynamic: requires-python
Dynamic: summary
